CHANGELOG.txt
MANIFEST.in
README.txt
ez_setup.py
kurzfile.kpf
setup.cfg
setup.py
kurzfile/__init__.py
kurzfile/api.py
kurzfile/constants.py
kurzfile/release.py
kurzfile/util.py
kurzfile.egg-info/PKG-INFO
kurzfile.egg-info/SOURCES.txt
kurzfile.egg-info/dependency_links.txt
kurzfile.egg-info/entry_points.txt
kurzfile.egg-info/top_level.txt
kurzfile.egg-info/zip-safe
kurzfile/scripts/__init__.py
kurzfile/scripts/k2list.py
scripts/make_krzlistings.sh
tools/kurzfile.nsi
tools/mkexe.bat