Metadata-Version: 1.0
Name: kurzfile
Version: 0.3a
Summary: A library to handle Kurzweil K-series synthesizer object files.
Home-page: http://chrisarndt.de/projects/python-kurzfile/
Author: Christopher Arndt
Author-email: chris@chrisarndt.de
License: MIT License
Download-URL: http://chrisarndt.de/projects/python-kurzfile/download/
Keywords: kurzweil,music
Platform: POSIX
Platform: Windows
Platform: MacOS X
Classifier: Development Status :: 3 - Alpha
Classifier: Environment :: Console
Classifier: Intended Audience :: Developers
Classifier: Intended Audience :: End Users/Desktop
Classifier: License :: OSI Approved :: BSD License
Classifier: Operating System :: Microsoft :: Windows
Classifier: Operating System :: POSIX
Classifier: Operating System :: MacOS :: MacOS X
Classifier: Programming Language :: Python
Classifier: Topic :: Multimedia :: Sound/Audio
Classifier: Topic :: Utilities
